prompt508/__init__.py
prompt508/cli.py
prompt508/core/__init__.py
prompt508/core/accessibility.py
prompt508/core/advisor.py
prompt508/core/jargon.py
prompt508/core/readability.py
prompt508/core/rewriter.py
prompt508/core/tone.py
prompt508/core/utils.py
prompt508/core/rules/gov_plain_language.json
prompt508/core/rules/replacements.json
prompt508/core/rules/section508.json
prompt508/examples/ai_rewriter_example.py
prompt508/examples/basic_usage.py
prompt508/examples/two_stage_pipeline.py
prompt508-0.2.0.dist-info/licenses/LICENSE
prompt508-0.2.0.dist-info/METADATA
prompt508-0.2.0.dist-info/WHEEL
prompt508-0.2.0.dist-info/entry_points.txt
prompt508-0.2.0.dist-info/top_level.txt
prompt508-0.2.0.dist-info/RECORD
