Metadata-Version: 2.4
Name: prompt508
Version: 0.2.0
Summary: Accessibility & Plain-Language Optimizer for AI Prompts - Section 508 Compliance with Two-Stage AI Pipeline
Author-email: Hung Manh Do <reach.hudo@gmail.com>
License: MIT
Project-URL: Homepage, https://github.com/hungmanhdo/prompt508
Project-URL: Documentation, https://github.com/hungmanhdo/prompt508#readme
Project-URL: Repository, https://github.com/hungmanhdo/prompt508
Project-URL: Issues, https://github.com/hungmanhdo/prompt508/issues
Keywords: accessibility,section-508,plain-language,ai,prompts,nlp,compliance
Classifier: Development Status :: 3 - Alpha
Classifier: Intended Audience :: Developers
Classifier: License :: OSI Approved :: MIT License
Classifier: Programming Language :: Python :: 3
Classifier: Programming Language :: Python :: 3.8
Classifier: Programming Language :: Python :: 3.9
Classifier: Programming Language :: Python :: 3.10
Classifier: Programming Language :: Python :: 3.11
Classifier: Programming Language :: Python :: 3.12
Classifier: Topic :: Software Development :: Libraries :: Python Modules
Classifier: Topic :: Text Processing :: Linguistic
Requires-Python: >=3.8
License-File: LICENSE
Requires-Dist: textstat>=0.7.3
Requires-Dist: spacy>=3.0.0
Requires-Dist: textblob>=0.17.1
Requires-Dist: typer>=0.9.0
Requires-Dist: pyyaml>=6.0
Requires-Dist: rich>=13.0.0
Requires-Dist: openai>=1.0.0
Requires-Dist: python-dotenv>=1.0.0
Provides-Extra: dev
Requires-Dist: pytest>=7.0.0; extra == "dev"
Requires-Dist: pytest-cov>=4.0.0; extra == "dev"
Requires-Dist: black>=23.0.0; extra == "dev"
Requires-Dist: flake8>=6.0.0; extra == "dev"
Requires-Dist: mypy>=1.0.0; extra == "dev"
Provides-Extra: all
Requires-Dist: prompt508[dev,llm]; extra == "all"
Dynamic: license-file
